enerplex/__init__.py
enerplex/api.py
enerplex/interface/__init__.py
enerplex/interface/dbclasses.py
enerplex/interface/responses.py
enerplex/utils/__init__.py
enerplex/utils/helpers.py
enerplex/utils/logger.py
tests/__init__.py
enerplex-0.2.2.dist-info/LICENSE
enerplex-0.2.2.dist-info/METADATA
enerplex-0.2.2.dist-info/WHEEL
enerplex-0.2.2.dist-info/top_level.txt
enerplex-0.2.2.dist-info/zip-safe
enerplex-0.2.2.dist-info/RECORD
