Metadata-Version: 2.1
Name: enerplex
Version: 0.2.2
Summary: Enerplex API Client
Home-page: https://github.com/NoxelS/enerplex-api-client
Author: Noel Schwabenland
Author-email: noel@lusi.uni-sb.de
License: MIT License
Keywords: energen enerplex
Platform: UNKNOWN
Classifier: Development Status :: 3 - Alpha
Classifier: Intended Audience :: Science/Research
Classifier: License :: OSI Approved :: MIT License
Classifier: Programming Language :: Python
Classifier: Programming Language :: Python :: 3.9
Classifier: Programming Language :: Python :: 3.10
Classifier: Programming Language :: Python :: 3.11
Classifier: Programming Language :: Python :: 3.12
Classifier: Programming Language :: Python :: 3.13
Classifier: Topic :: Software Development :: Libraries
Classifier: Topic :: Scientific/Engineering
Requires-Python: >=3.9
License-File: LICENSE
Requires-Dist: requests>=2.25.0
